alibabacloud_ivpd20190625/__init__.py
alibabacloud_ivpd20190625/client.py
alibabacloud_ivpd20190625/models.py
alibabacloud_ivpd20190625_py2-1.5.0.dist-info/LICENSE
alibabacloud_ivpd20190625_py2-1.5.0.dist-info/METADATA
alibabacloud_ivpd20190625_py2-1.5.0.dist-info/WHEEL
alibabacloud_ivpd20190625_py2-1.5.0.dist-info/top_level.txt
alibabacloud_ivpd20190625_py2-1.5.0.dist-info/RECORD
