Metadata-Version: 2.1
Name: alibabacloud-ivpd20190625-py2
Version: 1.5.0
Summary: Alibaba Cloud Intelligent Visual Production (20190625) SDK Library for Python2
Home-page: https://github.com/aliyun/alibabacloud-python2-sdk
Author: Alibaba Cloud SDK
Author-email: sdk-team@alibabacloud.com
License: Apache License 2.0
Keywords: alibabacloud,ivpd20190625,py2
Platform: any
Classifier: Development Status :: 4 - Beta
Classifier: Intended Audience :: Developers
Classifier: License :: OSI Approved :: Apache Software License
Classifier: Programming Language :: Python
Classifier: Programming Language :: Python :: 2
Classifier: Programming Language :: Python :: 2.7
Classifier: Programming Language :: Python :: 3
Classifier: Programming Language :: Python :: 3.4
Classifier: Programming Language :: Python :: 3.5
Classifier: Programming Language :: Python :: 3.6
Classifier: Programming Language :: Python :: 3.7
Classifier: Programming Language :: Python :: 3.8
Classifier: Topic :: Software Development
Requires-Dist: alibabacloud-tea-util-py2 (<1.0.0,>=0.0.5)
Requires-Dist: alibabacloud-oss-sdk-py2 (<1.0.0,>=0.0.1)
Requires-Dist: alibabacloud-tea-rpc-py2 (<1.0.0,>=0.0.1)
Requires-Dist: alibabacloud-openplatform20191219-py2 (<1.0.0,>=0.0.1)
Requires-Dist: alibabacloud-oss-util-py2 (<1.0.0,>=0.0.1)
Requires-Dist: alibabacloud-tea-fileform-py2 (<1.0.0,>=0.0.1)
Requires-Dist: alibabacloud-tea-openapi-py2 (<1.0.0,>=0.1.1)
Requires-Dist: alibabacloud-openapi-util-py2 (<1.0.0,>=0.0.8)
Requires-Dist: alibabacloud-endpoint-util-py2 (<1.0.0,>=0.0.2)
